arxglue/__init__.py
arxglue/utils.py
arxglue-1.0.1.dist-info/licenses/LICENSE.txt
arxglue-1.0.1.dist-info/METADATA
arxglue-1.0.1.dist-info/WHEEL
arxglue-1.0.1.dist-info/top_level.txt
arxglue-1.0.1.dist-info/RECORD
